baseframe.cpython-39-arm-linux-gnueabihf.so
property.cpython-39-arm-linux-gnueabihf.so
sino/__init__.py
sino/scom/__init__.py
sino/scom/baseframe.pxd
sino/scom/baseframe.pyx
sino/scom/defines.py
sino/scom/exeptions.py
sino/scom/frame.py
sino/scom/property.pyx
sino/scom/scom.py
sino/scom/setup.py
sino/scom/version.py
sino/scom/device/__init__.py
sino/scom/device/bsp.py
sino/scom/device/devicefactory.py
sino/scom/device/scomdevice.py
sino/scom/device/variopower.py
sino/scom/device/xtender.py
sino/scom/device/common/__init__.py
sino/scom/device/common/paramproxycontainer.py
sino/scom/dman/__init__.py
sino/scom/dman/devicemanager.py
sino/scom/dman/devicenotifier.py
sino/scom/dman/devicesubscriber.py
sino/scom/exception/__init__.py
sino/scom/exception/readexception.py
sino/scom/exception/writeexception.py
sino/scom/scomlib/scom_data_link.c
sino/scom/scomlib/scom_data_link.h
sino/scom/scomlib/scom_init.c
sino/scom/scomlib/scom_init.h
sino/scom/scomlib/scom_port_c99.h
sino/scom/scomlib/scom_property.c
sino/scom/scomlib/scom_property.h
sino/scom/scomlib/vc_stdint.h
scom-0.8.0.dist-info/LICENSE.md
scom-0.8.0.dist-info/METADATA
scom-0.8.0.dist-info/WHEEL
scom-0.8.0.dist-info/top_level.txt
scom-0.8.0.dist-info/RECORD
