Metadata-Version: 2.1
Name: scom
Version: 0.8.0
Summary: Studer devices control library
Home-page: https://www.studer-innotec.com
Maintainer: HES-SO Valais, School of Engineering, Sion
Maintainer-email: thomas.sterren@hevs.ch
License: MIT
Project-URL: Bug Tracker, https://github.com/hesso-valais/scom/issues
Project-URL: Source Code, https://github.com/hesso-valais/scom
Classifier: Development Status :: 3 - Alpha
Classifier: Intended Audience :: Developers
Classifier: Intended Audience :: Information Technology
Classifier: Topic :: Software Development :: Libraries :: Python Modules
Classifier: License :: OSI Approved :: MIT License
Classifier: Programming Language :: Python :: 3.8
Classifier: Programming Language :: Python :: 3.9
Classifier: Operating System :: OS Independent
License-File: LICENSE.md
